pyzabbix/__init__.py
pyzabbix/api.py
pyzabbix/logger.py
pyzabbix/sender.py
pyzabbix/version.py
zabbix/__init__.py
zabbix/api.py
zabbix/sender.py
py_zabbix-1.1.6.dist-info/LICENSE
py_zabbix-1.1.6.dist-info/METADATA
py_zabbix-1.1.6.dist-info/WHEEL
py_zabbix-1.1.6.dist-info/top_level.txt
py_zabbix-1.1.6.dist-info/RECORD
