Metadata-Version: 2.1
Name: py-zabbix
Version: 1.1.6
Summary: Python module to work with zabbix.
Home-page: https://github.com/blacked/py-zabbix
Author: Alexey Dubkov
Author-email: alexey.dubkov@gmail.com
License: UNKNOWN
Platform: UNKNOWN
Classifier: Development Status :: 5 - Production/Stable
Classifier: License :: OSI Approved :: GNU General Public License v2 (GPLv2)
Classifier: Programming Language :: Python :: 2
Classifier: Programming Language :: Python :: 3
Classifier: Topic :: System :: Monitoring
Classifier: Topic :: System :: Networking :: Monitoring
Classifier: Topic :: System :: Systems Administration
